openDateRange/__init__.py
openDateRange/date_range.py
openDateRange/range_borders.py
OpenDateRange-1.0.1.dist-info/LICENSE
OpenDateRange-1.0.1.dist-info/METADATA
OpenDateRange-1.0.1.dist-info/WHEEL
OpenDateRange-1.0.1.dist-info/top_level.txt
OpenDateRange-1.0.1.dist-info/RECORD
