Metadata-Version: 2.1
Name: OpenDateRange
Version: 1.0.1
License: MIT License        
Project-URL: Homepage, https://github.com/tlie03/OpenDateRange
Requires-Python: >=2.7.18
License-File: LICENSE
